data_exports/admin.py
data_exports/urls.py
data_exports/settings.py
data_exports/__init__.py
data_exports/forms.py
data_exports/test_settings.py
data_exports/models.py
data_exports/tests.py
data_exports/views.py
data_exports/test_urls.py
data_exports/compat.py
data_exports/templates/data_exports/export_detail.html
data_exports/templates/data_exports/export_form.html
data_exports/templates/data_exports/base.html
data_exports/templates/data_exports/export_cols.html
data_exports/templates/data_exports/export_detail_csv.html
data_exports/templatetags/getter_tags.py
data_exports/templatetags/__init__.py
data_exports/migrations/0002_auto__add_format__add_field_export_export_format.py
data_exports/migrations/0001_initial.py
data_exports/migrations/__init__.py
data_exports/migrations/0007_auto__chg_field_column_label.py
data_exports/migrations/0006_auto__add_unique_export_slug.py
data_exports/migrations/0004_auto__del_field_export_display_labels.py
data_exports/migrations/0005_auto__del_field_format_attachment__add_field_format_file_ext.py
data_exports/migrations/0003_auto__add_field_column_order.py
django_data_exports-0.7.dist-info/metadata.json
django_data_exports-0.7.dist-info/METADATA
django_data_exports-0.7.dist-info/RECORD
django_data_exports-0.7.dist-info/WHEEL
django_data_exports-0.7.dist-info/DESCRIPTION.rst
django_data_exports-0.7.dist-info/top_level.txt
